<pkg-contents spec="1.12"><f n="DSTROOT" o="lrz" g="staff" p="16877" pt="/Users/lrz/src/BridgeSupport/DSTROOT" m="false" t="file"><f n="System" o="root" g="wheel" p="16877"><f n="Library" o="root" g="wheel" p="16877"><f n="BridgeSupport" o="root" g="wheel" p="16877"><f n="include" o="root" g="wheel" p="16877"><f n="BSMacTypes.h" o="root" g="wheel" p="33188"/><f n="objc" o="root" g="wheel" p="16877"><f n="objc.h" o="root" g="wheel" p="33188"/></f></f><f n="libSystem.bridgesupport" o="root" g="wheel" p="33188"/><f n="ruby-1.8" o="root" g="wheel" p="16877"><f n="bridgesupportparser.bundle" o="root" g="wheel" p="33261"/><f n="bridgesupportparser.rb" o="root" g="wheel" p="33188"/></f></f><f n="DTDs" o="root" g="wheel" p="16877"><f n="BridgeSupport.dtd" o="root" g="wheel" p="33188"/></f><f n="Frameworks" o="root" g="wheel" p="16877"><f n="Accelerate.framework" o="root" g="wheel" p="16877"><f n="Versions" o="root" g="wheel" p="16877"><f n="A" o="root" g="wheel" p="16877"><f n="Frameworks" o="root" g="wheel" p="16877"><f n="vImage.framework" o="root" g="wheel" p="16877"><f n="Versions" o="root" g="wheel" p="16877"><f n="A" o="root" g="wheel" p="16877"><f n="Resources" o="root" g="wheel" p="16877"><f n="BridgeSupport" o="root" g="wheel" p="16877"><f n="vImage.bridgesupport" o="root" g="wheel" p="33188"/></f></f></f></f></f></f><f n="Resources" o="root" g="wheel" p="16877"><f n="BridgeSupport" o="root" g="wheel" p="16877"><f n="Accelerate.bridgesupport" o="root" g="wheel" p="33188"/></f></f></f></f></f><f n="AddressBook.framework" o="root" g="wheel" p="16877"><f n="Versions" o="root" g="wheel" p="16877"><f n="A" o="root" g="wheel" p="16877"><f n="Resources" o="root" g="wheel" p="16877"><f n="BridgeSupport" o="root" g="wheel" p="16877"><f n="AddressBook.bridgesupport" o="root" g="wheel" p="33188"/></f></f></f></f></f><f n="AGL.framework" o="root" g="wheel" p="16877"><f n="Versions" o="root" g="wheel" p="16877"><f n="A" o="root" g="wheel" p="16877"><f n="Resources" o="root" g="wheel" p="16877"><f n="BridgeSupport" o="root" g="wheel" p="16877"><f n="AGL.bridgesupport" o="root" g="wheel" p="33188"/></f></f></f></f></f><f n="AppKit.framework" o="root" g="wheel" p="16877"><f n="Versions" o="root" g="wheel" p="16877"><f n="C" o="root" g="wheel" p="16877"><f n="Resources" o="root" g="wheel" p="16877"><f n="BridgeSupport" o="root" g="wheel" p="16877"><f n="AppKit.bridgesupport" o="root" g="wheel" p="33188"/><f n="AppKit.dylib" o="root" g="wheel" p="33261"/></f></f></f></f></f><f n="AppKitScripting.framework" o="root" g="wheel" p="16877"><f n="Versions" o="root" g="wheel" p="16877"><f n="A" o="root" g="wheel" p="16877"><f n="Resources" o="root" g="wheel" p="16877"><f n="BridgeSupport" o="root" g="wheel" p="16877"><f n="AppKitScripting.bridgesupport" o="root" g="wheel" p="33188"/></f></f></f></f></f><f n="AppleScriptKit.framework" o="root" g="wheel" p="16877"><f n="Versions" o="root" g="wheel" p="16877"><f n="A" o="root" g="wheel" p="16877"><f n="Resources" o="root" g="wheel" p="16877"><f n="BridgeSupport" o="root" g="wheel" p="16877"><f n="AppleScriptKit.bridgesupport" o="root" g="wheel" p="33188"/></f></f></f></f></f><f n="AppleScriptObjC.framework" o="root" g="wheel" p="16877"><f n="Versions" o="root" g="wheel" p="16877"><f n="A" o="root" g="wheel" p="16877"><f n="Resources" o="root" g="wheel" p="16877"><f n="BridgeSupport" o="root" g="wheel" p="16877"><f n="AppleScriptObjC.bridgesupport" o="root" g="wheel" p="33188"/></f></f></f></f></f><f n="AppleShareClientCore.framework" o="root" g="wheel" p="16877"><f n="Versions" o="root" g="wheel" p="16877"><f n="A" o="root" g="wheel" p="16877"><f n="Resources" o="root" g="wheel" p="16877"><f n="BridgeSupport" o="root" g="wheel" p="16877"><f n="AppleShareClientCore.bridgesupport" o="root" g="wheel" p="33188"/></f></f></f></f></f><f n="ApplicationServices.framework" o="root" g="wheel" p="16877"><f n="Versions" o="root" g="wheel" p="16877"><f n="A" o="root" g="wheel" p="16877"><f n="Frameworks" o="root" g="wheel" p="16877"><f n="ATS.framework" o="root" g="wheel" p="16877"><f n="Versions" o="root" g="wheel" p="16877"><f n="A" o="root" g="wheel" p="16877"><f n="Resources" o="root" g="wheel" p="16877"><f n="BridgeSupport" o="root" g="wheel" p="16877"><f n="ATS.bridgesupport" o="root" g="wheel" p="33188"/></f></f></f></f></f><f n="ColorSync.framework" o="root" g="wheel" p="16877"><f n="Versions" o="root" g="wheel" p="16877"><f n="A" o="root" g="wheel" p="16877"><f n="Resources" o="root" g="wheel" p="16877"><f n="BridgeSupport" o="root" g="wheel" p="16877"><f n="ColorSync.bridgesupport" o="root" g="wheel" p="33188"/><f n="ColorSync.dylib" o="root" g="wheel" p="33261"/></f></f></f></f></f><f n="CoreGraphics.framework" o="root" g="wheel" p="16877"><f n="Versions" o="root" g="wheel" p="16877"><f n="A" o="root" g="wheel" p="16877"><f n="Resources" o="root" g="wheel" p="16877"><f n="BridgeSupport" o="root" g="wheel" p="16877"><f n="CoreGraphics.bridgesupport" o="root" g="wheel" p="33188"/><f n="CoreGraphics.dylib" o="root" g="wheel" p="33261"/></f></f></f></f></f><f n="CoreText.framework" o="root" g="wheel" p="16877"><f n="Versions" o="root" g="wheel" p="16877"><f n="A" o="root" g="wheel" p="16877"><f n="Resources" o="root" g="wheel" p="16877"><f n="BridgeSupport" o="root" g="wheel" p="16877"><f n="CoreText.bridgesupport" o="root" g="wheel" p="33188"/></f></f></f></f></f><f n="HIServices.framework" o="root" g="wheel" p="16877"><f n="Versions" o="root" g="wheel" p="16877"><f n="A" o="root" g="wheel" p="16877"><f n="Resources" o="root" g="wheel" p="16877"><f n="BridgeSupport" o="root" g="wheel" p="16877"><f n="HIServices.bridgesupport" o="root" g="wheel" p="33188"/></f></f></f></f></f><f n="ImageIO.framework" o="root" g="wheel" p="16877"><f n="Versions" o="root" g="wheel" p="16877"><f n="A" o="root" g="wheel" p="16877"><f n="Resources" o="root" g="wheel" p="16877"><f n="BridgeSupport" o="root" g="wheel" p="16877"><f n="ImageIO.bridgesupport" o="root" g="wheel" p="33188"/></f></f></f></f></f><f n="LangAnalysis.framework" o="root" g="wheel" p="16877"><f n="Versions" o="root" g="wheel" p="16877"><f n="A" o="root" g="wheel" p="16877"><f n="Resources" o="root" g="wheel" p="16877"><f n="BridgeSupport" o="root" g="wheel" p="16877"><f n="LangAnalysis.bridgesupport" o="root" g="wheel" p="33188"/></f></f></f></f></f><f n="PrintCore.framework" o="root" g="wheel" p="16877"><f n="Versions" o="root" g="wheel" p="16877"><f n="A" o="root" g="wheel" p="16877"><f n="Resources" o="root" g="wheel" p="16877"><f n="BridgeSupport" o="root" g="wheel" p="16877"><f n="PrintCore.bridgesupport" o="root" g="wheel" p="33188"/></f></f></f></f></f><f n="QD.framework" o="root" g="wheel" p="16877"><f n="Versions" o="root" g="wheel" p="16877"><f n="A" o="root" g="wheel" p="16877"><f n="Resources" o="root" g="wheel" p="16877"><f n="BridgeSupport" o="root" g="wheel" p="16877"><f n="QD.bridgesupport" o="root" g="wheel" p="33188"/></f></f></f></f></f><f n="SpeechSynthesis.framework" o="root" g="wheel" p="16877"><f n="Versions" o="root" g="wheel" p="16877"><f n="A" o="root" g="wheel" p="16877"><f n="Resources" o="root" g="wheel" p="16877"><f n="BridgeSupport" o="root" g="wheel" p="16877"><f n="SpeechSynthesis.bridgesupport" o="root" g="wheel" p="33188"/></f></f></f></f></f></f><f n="Resources" o="root" g="wheel" p="16877"><f n="BridgeSupport" o="root" g="wheel" p="16877"><f n="ApplicationServices.bridgesupport" o="root" g="wheel" p="33188"/></f></f></f></f></f><f n="AudioToolbox.framework" o="root" g="wheel" p="16877"><f n="Versions" o="root" g="wheel" p="16877"><f n="A" o="root" g="wheel" p="16877"><f n="Resources" o="root" g="wheel" p="16877"><f n="BridgeSupport" o="root" g="wheel" p="16877"><f n="AudioToolbox.bridgesupport" o="root" g="wheel" p="33188"/><f n="AudioToolbox.dylib" o="root" g="wheel" p="33261"/></f></f></f></f></f><f n="AudioUnit.framework" o="root" g="wheel" p="16877"><f n="Versions" o="root" g="wheel" p="16877"><f n="A" o="root" g="wheel" p="16877"><f n="Resources" o="root" g="wheel" p="16877"><f n="BridgeSupport" o="root" g="wheel" p="16877"><f n="AudioUnit.bridgesupport" o="root" g="wheel" p="33188"/></f></f></f></f></f><f n="Automator.framework" o="root" g="wheel" p="16877"><f n="Versions" o="root" g="wheel" p="16877"><f n="A" o="root" g="wheel" p="16877"><f n="Resources" o="root" g="wheel" p="16877"><f n="BridgeSupport" o="root" g="wheel" p="16877"><f n="Automator.bridgesupport" o="root" g="wheel" p="33188"/></f></f></f></f></f><f n="CalendarStore.framework" o="root" g="wheel" p="16877"><f n="Versions" o="root" g="wheel" p="16877"><f n="A" o="root" g="wheel" p="16877"><f n="Resources" o="root" g="wheel" p="16877"><f n="BridgeSupport" o="root" g="wheel" p="16877"><f n="CalendarStore.bridgesupport" o="root" g="wheel" p="33188"/></f></f></f></f></f><f n="Carbon.framework" o="root" g="wheel" p="16877"><f n="Versions" o="root" g="wheel" p="16877"><f n="A" o="root" g="wheel" p="16877"><f n="Frameworks" o="root" g="wheel" p="16877"><f n="CarbonSound.framework" o="root" g="wheel" p="16877"><f n="Versions" o="root" g="wheel" p="16877"><f n="A" o="root" g="wheel" p="16877"><f n="Resources" o="root" g="wheel" p="16877"><f n="BridgeSupport" o="root" g="wheel" p="16877"><f n="CarbonSound.bridgesupport" o="root" g="wheel" p="33188"/></f></f></f></f></f><f n="CommonPanels.framework" o="root" g="wheel" p="16877"><f n="Versions" o="root" g="wheel" p="16877"><f n="A" o="root" g="wheel" p="16877"><f n="Resources" o="root" g="wheel" p="16877"><f n="BridgeSupport" o="root" g="wheel" p="16877"><f n="CommonPanels.bridgesupport" o="root" g="wheel" p="33188"/></f></f></f></f></f><f n="Help.framework" o="root" g="wheel" p="16877"><f n="Versions" o="root" g="wheel" p="16877"><f n="A" o="root" g="wheel" p="16877"><f n="Resources" o="root" g="wheel" p="16877"><f n="BridgeSupport" o="root" g="wheel" p="16877"><f n="Help.bridgesupport" o="root" g="wheel" p="33188"/></f></f></f></f></f><f n="HIToolbox.framework" o="root" g="wheel" p="16877"><f n="Versions" o="root" g="wheel" p="16877"><f n="A" o="root" g="wheel" p="16877"><f n="Resources" o="root" g="wheel" p="16877"><f n="BridgeSupport" o="root" g="wheel" p="16877"><f n="HIToolbox.bridgesupport" o="root" g="wheel" p="33188"/></f></f></f></f></f><f n="HTMLRendering.framework" o="root" g="wheel" p="16877"><f n="Versions" o="root" g="wheel" p="16877"><f n="A" o="root" g="wheel" p="16877"><f n="Resources" o="root" g="wheel" p="16877"><f n="BridgeSupport" o="root" g="wheel" p="16877"><f n="HTMLRendering.bridgesupport" o="root" g="wheel" p="33188"/></f></f></f></f></f><f n="ImageCapture.framework" o="root" g="wheel" p="16877"><f n="Versions" o="root" g="wheel" p="16877"><f n="A" o="root" g="wheel" p="16877"><f n="Resources" o="root" g="wheel" p="16877"><f n="BridgeSupport" o="root" g="wheel" p="16877"><f n="ImageCapture.bridgesupport" o="root" g="wheel" p="33188"/></f></f></f></f></f><f n="Ink.framework" o="root" g="wheel" p="16877"><f n="Versions" o="root" g="wheel" p="16877"><f n="A" o="root" g="wheel" p="16877"><f n="Resources" o="root" g="wheel" p="16877"><f n="BridgeSupport" o="root" g="wheel" p="16877"><f n="Ink.bridgesupport" o="root" g="wheel" p="33188"/></f></f></f></f></f><f n="NavigationServices.framework" o="root" g="wheel" p="16877"><f n="Versions" o="root" g="wheel" p="16877"><f n="A" o="root" g="wheel" p="16877"><f n="Resources" o="root" g="wheel" p="16877"><f n="BridgeSupport" o="root" g="wheel" p="16877"><f n="NavigationServices.bridgesupport" o="root" g="wheel" p="33188"/></f></f></f></f></f><f n="OpenScripting.framework" o="root" g="wheel" p="16877"><f n="Versions" o="root" g="wheel" p="16877"><f n="A" o="root" g="wheel" p="16877"><f n="Resources" o="root" g="wheel" p="16877"><f n="BridgeSupport" o="root" g="wheel" p="16877"><f n="OpenScripting.bridgesupport" o="root" g="wheel" p="33188"/></f></f></f></f></f><f n="Print.framework" o="root" g="wheel" p="16877"><f n="Versions" o="root" g="wheel" p="16877"><f n="A" o="root" g="wheel" p="16877"><f n="Resources" o="root" g="wheel" p="16877"><f n="BridgeSupport" o="root" g="wheel" p="16877"><f n="Print.bridgesupport" o="root" g="wheel" p="33188"/></f></f></f></f></f><f n="SecurityHI.framework" o="root" g="wheel" p="16877"><f n="Versions" o="root" g="wheel" p="16877"><f n="A" o="root" g="wheel" p="16877"><f n="Resources" o="root" g="wheel" p="16877"><f n="BridgeSupport" o="root" g="wheel" p="16877"><f n="SecurityHI.bridgesupport" o="root" g="wheel" p="33188"/></f></f></f></f></f><f n="SpeechRecognition.framework" o="root" g="wheel" p="16877"><f n="Versions" o="root" g="wheel" p="16877"><f n="A" o="root" g="wheel" p="16877"><f n="Resources" o="root" g="wheel" p="16877"><f n="BridgeSupport" o="root" g="wheel" p="16877"><f n="SpeechRecognition.bridgesupport" o="root" g="wheel" p="33188"/></f></f></f></f></f></f><f n="Resources" o="root" g="wheel" p="16877"><f n="BridgeSupport" o="root" g="wheel" p="16877"><f n="Carbon.bridgesupport" o="root" g="wheel" p="33188"/></f></f></f></f></f><f n="Cocoa.framework" o="root" g="wheel" p="16877"><f n="Versions" o="root" g="wheel" p="16877"><f n="A" o="root" g="wheel" p="16877"><f n="Resources" o="root" g="wheel" p="16877"><f n="BridgeSupport" o="root" g="wheel" p="16877"><f n="Cocoa.bridgesupport" o="root" g="wheel" p="33188"/></f></f></f></f></f><f n="Collaboration.framework" o="root" g="wheel" p="16877"><f n="Versions" o="root" g="wheel" p="16877"><f n="A" o="root" g="wheel" p="16877"><f n="Resources" o="root" g="wheel" p="16877"><f n="BridgeSupport" o="root" g="wheel" p="16877"><f n="Collaboration.bridgesupport" o="root" g="wheel" p="33188"/></f></f></f></f></f><f n="CoreAudio.framework" o="root" g="wheel" p="16877"><f n="Versions" o="root" g="wheel" p="16877"><f n="A" o="root" g="wheel" p="16877"><f n="Resources" o="root" g="wheel" p="16877"><f n="BridgeSupport" o="root" g="wheel" p="16877"><f n="CoreAudio.bridgesupport" o="root" g="wheel" p="33188"/></f></f></f></f></f><f n="CoreAudioKit.framework" o="root" g="wheel" p="16877"><f n="Versions" o="root" g="wheel" p="16877"><f n="A" o="root" g="wheel" p="16877"><f n="Resources" o="root" g="wheel" p="16877"><f n="BridgeSupport" o="root" g="wheel" p="16877"><f n="CoreAudioKit.bridgesupport" o="root" g="wheel" p="33188"/></f></f></f></f></f><f n="CoreData.framework" o="root" g="wheel" p="16877"><f n="Versions" o="root" g="wheel" p="16877"><f n="A" o="root" g="wheel" p="16877"><f n="Resources" o="root" g="wheel" p="16877"><f n="BridgeSupport" o="root" g="wheel" p="16877"><f n="CoreData.bridgesupport" o="root" g="wheel" p="33188"/></f></f></f></f></f><f n="CoreFoundation.framework" o="root" g="wheel" p="16877"><f n="Versions" o="root" g="wheel" p="16877"><f n="A" o="root" g="wheel" p="16877"><f n="Resources" o="root" g="wheel" p="16877"><f n="BridgeSupport" o="root" g="wheel" p="16877"><f n="CoreFoundation.bridgesupport" o="root" g="wheel" p="33188"/><f n="CoreFoundation.dylib" o="root" g="wheel" p="33261"/></f></f></f></f></f><f n="CoreLocation.framework" o="root" g="wheel" p="16877"><f n="Versions" o="root" g="wheel" p="16877"><f n="A" o="root" g="wheel" p="16877"><f n="Resources" o="root" g="wheel" p="16877"><f n="BridgeSupport" o="root" g="wheel" p="16877"><f n="CoreLocation.bridgesupport" o="root" g="wheel" p="33188"/></f></f></f></f></f><f n="CoreMIDI.framework" o="root" g="wheel" p="16877"><f n="Versions" o="root" g="wheel" p="16877"><f n="A" o="root" g="wheel" p="16877"><f n="Resources" o="root" g="wheel" p="16877"><f n="BridgeSupport" o="root" g="wheel" p="16877"><f n="CoreMIDI.bridgesupport" o="root" g="wheel" p="33188"/></f></f></f></f></f><f n="CoreServices.framework" o="root" g="wheel" p="16877"><f n="Versions" o="root" g="wheel" p="16877"><f n="A" o="root" g="wheel" p="16877"><f n="Frameworks" o="root" g="wheel" p="16877"><f n="AE.framework" o="root" g="wheel" p="16877"><f n="Versions" o="root" g="wheel" p="16877"><f n="A" o="root" g="wheel" p="16877"><f n="Resources" o="root" g="wheel" p="16877"><f n="BridgeSupport" o="root" g="wheel" p="16877"><f n="AE.bridgesupport" o="root" g="wheel" p="33188"/></f></f></f></f></f><f n="CarbonCore.framework" o="root" g="wheel" p="16877"><f n="Versions" o="root" g="wheel" p="16877"><f n="A" o="root" g="wheel" p="16877"><f n="Resources" o="root" g="wheel" p="16877"><f n="BridgeSupport" o="root" g="wheel" p="16877"><f n="CarbonCore.bridgesupport" o="root" g="wheel" p="33188"/></f></f></f></f></f><f n="CFNetwork.framework" o="root" g="wheel" p="16877"><f n="Versions" o="root" g="wheel" p="16877"><f n="A" o="root" g="wheel" p="16877"><f n="Resources" o="root" g="wheel" p="16877"><f n="BridgeSupport" o="root" g="wheel" p="16877"><f n="CFNetwork.bridgesupport" o="root" g="wheel" p="33188"/><f n="CFNetwork.dylib" o="root" g="wheel" p="33261"/></f></f></f></f></f><f n="DictionaryServices.framework" o="root" g="wheel" p="16877"><f n="Versions" o="root" g="wheel" p="16877"><f n="A" o="root" g="wheel" p="16877"><f n="Resources" o="root" g="wheel" p="16877"><f n="BridgeSupport" o="root" g="wheel" p="16877"><f n="DictionaryServices.bridgesupport" o="root" g="wheel" p="33188"/></f></f></f></f></f><f n="LaunchServices.framework" o="root" g="wheel" p="16877"><f n="Versions" o="root" g="wheel" p="16877"><f n="A" o="root" g="wheel" p="16877"><f n="Resources" o="root" g="wheel" p="16877"><f n="BridgeSupport" o="root" g="wheel" p="16877"><f n="LaunchServices.bridgesupport" o="root" g="wheel" p="33188"/></f></f></f></f></f><f n="Metadata.framework" o="root" g="wheel" p="16877"><f n="Versions" o="root" g="wheel" p="16877"><f n="A" o="root" g="wheel" p="16877"><f n="Resources" o="root" g="wheel" p="16877"><f n="BridgeSupport" o="root" g="wheel" p="16877"><f n="Metadata.bridgesupport" o="root" g="wheel" p="33188"/></f></f></f></f></f><f n="OSServices.framework" o="root" g="wheel" p="16877"><f n="Versions" o="root" g="wheel" p="16877"><f n="A" o="root" g="wheel" p="16877"><f n="Resources" o="root" g="wheel" p="16877"><f n="BridgeSupport" o="root" g="wheel" p="16877"><f n="OSServices.bridgesupport" o="root" g="wheel" p="33188"/></f></f></f></f></f><f n="SearchKit.framework" o="root" g="wheel" p="16877"><f n="Versions" o="root" g="wheel" p="16877"><f n="A" o="root" g="wheel" p="16877"><f n="Resources" o="root" g="wheel" p="16877"><f n="BridgeSupport" o="root" g="wheel" p="16877"><f n="SearchKit.bridgesupport" o="root" g="wheel" p="33188"/></f></f></f></f></f></f><f n="Resources" o="root" g="wheel" p="16877"><f n="BridgeSupport" o="root" g="wheel" p="16877"><f n="CoreServices.bridgesupport" o="root" g="wheel" p="33188"/></f></f></f></f></f><f n="CoreVideo.framework" o="root" g="wheel" p="16877"><f n="Versions" o="root" g="wheel" p="16877"><f n="A" o="root" g="wheel" p="16877"><f n="Resources" o="root" g="wheel" p="16877"><f n="BridgeSupport" o="root" g="wheel" p="16877"><f n="CoreVideo.bridgesupport" o="root" g="wheel" p="33188"/></f></f></f></f></f><f n="CoreWLAN.framework" o="root" g="wheel" p="16877"><f n="Versions" o="root" g="wheel" p="16877"><f n="A" o="root" g="wheel" p="16877"><f n="Resources" o="root" g="wheel" p="16877"><f n="BridgeSupport" o="root" g="wheel" p="16877"><f n="CoreWLAN.bridgesupport" o="root" g="wheel" p="33188"/></f></f></f></f></f><f n="DirectoryService.framework" o="root" g="wheel" p="16877"><f n="Versions" o="root" g="wheel" p="16877"><f n="A" o="root" g="wheel" p="16877"><f n="Resources" o="root" g="wheel" p="16877"><f n="BridgeSupport" o="root" g="wheel" p="16877"><f n="DirectoryService.bridgesupport" o="root" g="wheel" p="33188"/></f></f></f></f></f><f n="DiscRecording.framework" o="root" g="wheel" p="16877"><f n="Versions" o="root" g="wheel" p="16877"><f n="A" o="root" g="wheel" p="16877"><f n="Resources" o="root" g="wheel" p="16877"><f n="BridgeSupport" o="root" g="wheel" p="16877"><f n="DiscRecording.bridgesupport" o="root" g="wheel" p="33188"/></f></f></f></f></f><f n="DiscRecordingUI.framework" o="root" g="wheel" p="16877"><f n="Versions" o="root" g="wheel" p="16877"><f n="A" o="root" g="wheel" p="16877"><f n="Resources" o="root" g="wheel" p="16877"><f n="BridgeSupport" o="root" g="wheel" p="16877"><f n="DiscRecordingUI.bridgesupport" o="root" g="wheel" p="33188"/></f></f></f></f></f><f n="DiskArbitration.framework" o="root" g="wheel" p="16877"><f n="Versions" o="root" g="wheel" p="16877"><f n="A" o="root" g="wheel" p="16877"><f n="Resources" o="root" g="wheel" p="16877"><f n="BridgeSupport" o="root" g="wheel" p="16877"><f n="DiskArbitration.bridgesupport" o="root" g="wheel" p="33188"/></f></f></f></f></f><f n="DrawSprocket.framework" o="root" g="wheel" p="16877"><f n="Versions" o="root" g="wheel" p="16877"><f n="A" o="root" g="wheel" p="16877"><f n="Resources" o="root" g="wheel" p="16877"><f n="BridgeSupport" o="root" g="wheel" p="16877"><f n="DrawSprocket.bridgesupport" o="root" g="wheel" p="33188"/></f></f></f></f></f><f n="DVComponentGlue.framework" o="root" g="wheel" p="16877"><f n="Versions" o="root" g="wheel" p="16877"><f n="A" o="root" g="wheel" p="16877"><f n="Resources" o="root" g="wheel" p="16877"><f n="BridgeSupport" o="root" g="wheel" p="16877"><f n="DVComponentGlue.bridgesupport" o="root" g="wheel" p="33188"/></f></f></f></f></f><f n="DVDPlayback.framework" o="root" g="wheel" p="16877"><f n="Versions" o="root" g="wheel" p="16877"><f n="A" o="root" g="wheel" p="16877"><f n="Resources" o="root" g="wheel" p="16877"><f n="BridgeSupport" o="root" g="wheel" p="16877"><f n="DVDPlayback.bridgesupport" o="root" g="wheel" p="33188"/></f></f></f></f></f><f n="ExceptionHandling.framework" o="root" g="wheel" p="16877"><f n="Versions" o="root" g="wheel" p="16877"><f n="A" o="root" g="wheel" p="16877"><f n="Resources" o="root" g="wheel" p="16877"><f n="BridgeSupport" o="root" g="wheel" p="16877"><f n="ExceptionHandling.bridgesupport" o="root" g="wheel" p="33188"/></f></f></f></f></f><f n="ForceFeedback.framework" o="root" g="wheel" p="16877"><f n="Versions" o="root" g="wheel" p="16877"><f n="A" o="root" g="wheel" p="16877"><f n="Resources" o="root" g="wheel" p="16877"><f n="BridgeSupport" o="root" g="wheel" p="16877"><f n="ForceFeedback.bridgesupport" o="root" g="wheel" p="33188"/></f></f></f></f></f><f n="Foundation.framework" o="root" g="wheel" p="16877"><f n="Versions" o="root" g="wheel" p="16877"><f n="C" o="root" g="wheel" p="16877"><f n="Resources" o="root" g="wheel" p="16877"><f n="BridgeSupport" o="root" g="wheel" p="16877"><f n="Foundation.bridgesupport" o="root" g="wheel" p="33188"/><f n="Foundation.dylib" o="root" g="wheel" p="33261"/></f></f></f></f></f><f n="FWAUserLib.framework" o="root" g="wheel" p="16877"><f n="Versions" o="root" g="wheel" p="16877"><f n="A" o="root" g="wheel" p="16877"><f n="Resources" o="root" g="wheel" p="16877"><f n="BridgeSupport" o="root" g="wheel" p="16877"><f n="FWAUserLib.bridgesupport" o="root" g="wheel" p="33188"/></f></f></f></f></f><f n="GLUT.framework" o="root" g="wheel" p="16877"><f n="Versions" o="root" g="wheel" p="16877"><f n="A" o="root" g="wheel" p="16877"><f n="Resources" o="root" g="wheel" p="16877"><f n="BridgeSupport" o="root" g="wheel" p="16877"><f n="GLUT.bridgesupport" o="root" g="wheel" p="33188"/></f></f></f></f></f><f n="ICADevices.framework" o="root" g="wheel" p="16877"><f n="Versions" o="root" g="wheel" p="16877"><f n="A" o="root" g="wheel" p="16877"><f n="Resources" o="root" g="wheel" p="16877"><f n="BridgeSupport" o="root" g="wheel" p="16877"><f n="ICADevices.bridgesupport" o="root" g="wheel" p="33188"/></f></f></f></f></f><f n="ImageCaptureCore.framework" o="root" g="wheel" p="16877"><f n="Versions" o="root" g="wheel" p="16877"><f n="A" o="root" g="wheel" p="16877"><f n="Resources" o="root" g="wheel" p="16877"><f n="BridgeSupport" o="root" g="wheel" p="16877"><f n="ImageCaptureCore.bridgesupport" o="root" g="wheel" p="33188"/></f></f></f></f></f><f n="InputMethodKit.framework" o="root" g="wheel" p="16877"><f n="Versions" o="root" g="wheel" p="16877"><f n="A" o="root" g="wheel" p="16877"><f n="Resources" o="root" g="wheel" p="16877"><f n="BridgeSupport" o="root" g="wheel" p="16877"><f n="InputMethodKit.bridgesupport" o="root" g="wheel" p="33188"/></f></f></f></f></f><f n="InstallerPlugins.framework" o="root" g="wheel" p="16877"><f n="Versions" o="root" g="wheel" p="16877"><f n="A" o="root" g="wheel" p="16877"><f n="Resources" o="root" g="wheel" p="16877"><f n="BridgeSupport" o="root" g="wheel" p="16877"><f n="InstallerPlugins.bridgesupport" o="root" g="wheel" p="33188"/></f></f></f></f></f><f n="InstantMessage.framework" o="root" g="wheel" p="16877"><f n="Versions" o="root" g="wheel" p="16877"><f n="A" o="root" g="wheel" p="16877"><f n="Resources" o="root" g="wheel" p="16877"><f n="BridgeSupport" o="root" g="wheel" p="16877"><f n="InstantMessage.bridgesupport" o="root" g="wheel" p="33188"/></f></f></f></f></f><f n="IOBluetooth.framework" o="root" g="wheel" p="16877"><f n="Versions" o="root" g="wheel" p="16877"><f n="A" o="root" g="wheel" p="16877"><f n="Resources" o="root" g="wheel" p="16877"><f n="BridgeSupport" o="root" g="wheel" p="16877"><f n="IOBluetooth.bridgesupport" o="root" g="wheel" p="33188"/></f></f></f></f></f><f n="IOBluetoothUI.framework" o="root" g="wheel" p="16877"><f n="Versions" o="root" g="wheel" p="16877"><f n="A" o="root" g="wheel" p="16877"><f n="Resources" o="root" g="wheel" p="16877"><f n="BridgeSupport" o="root" g="wheel" p="16877"><f n="IOBluetoothUI.bridgesupport" o="root" g="wheel" p="33188"/></f></f></f></f></f><f n="IOSurface.framework" o="root" g="wheel" p="16877"><f n="Versions" o="root" g="wheel" p="16877"><f n="A" o="root" g="wheel" p="16877"><f n="Resources" o="root" g="wheel" p="16877"><f n="BridgeSupport" o="root" g="wheel" p="16877"><f n="IOSurface.bridgesupport" o="root" g="wheel" p="33188"/></f></f></f></f></f><f n="JavaFrameEmbedding.framework" o="root" g="wheel" p="16877"><f n="Versions" o="root" g="wheel" p="16877"><f n="A" o="root" g="wheel" p="16877"><f n="Resources" o="root" g="wheel" p="16877"><f n="BridgeSupport" o="root" g="wheel" p="16877"><f n="JavaFrameEmbedding.bridgesupport" o="root" g="wheel" p="33188"/></f></f></f></f></f><f n="JavaScriptCore.framework" o="root" g="wheel" p="16877"><f n="Versions" o="root" g="wheel" p="16877"><f n="A" o="root" g="wheel" p="16877"><f n="Resources" o="root" g="wheel" p="16877"><f n="BridgeSupport" o="root" g="wheel" p="16877"><f n="JavaScriptCore.bridgesupport" o="root" g="wheel" p="33188"/></f></f></f></f></f><f n="JavaVM.framework" o="root" g="wheel" p="16877"><f n="Versions" o="root" g="wheel" p="16877"><f n="A" o="root" g="wheel" p="16877"><f n="Frameworks" o="root" g="wheel" p="16877"><f n="JavaNativeFoundation.framework" o="root" g="wheel" p="16877"><f n="Versions" o="root" g="wheel" p="16877"><f n="A" o="root" g="wheel" p="16877"><f n="Resources" o="root" g="wheel" p="16877"><f n="BridgeSupport" o="root" g="wheel" p="16877"><f n="JavaNativeFoundation.bridgesupport" o="root" g="wheel" p="33188"/></f></f></f></f></f><f n="JavaRuntimeSupport.framework" o="root" g="wheel" p="16877"><f n="Versions" o="root" g="wheel" p="16877"><f n="A" o="root" g="wheel" p="16877"><f n="Resources" o="root" g="wheel" p="16877"><f n="BridgeSupport" o="root" g="wheel" p="16877"><f n="JavaRuntimeSupport.bridgesupport" o="root" g="wheel" p="33188"/></f></f></f></f></f></f><f n="Resources" o="root" g="wheel" p="16877"><f n="BridgeSupport" o="root" g="wheel" p="16877"><f n="JavaVM.bridgesupport" o="root" g="wheel" p="33188"/></f></f></f></f></f><f n="Kerberos.framework" o="root" g="wheel" p="16877"><f n="Versions" o="root" g="wheel" p="16877"><f n="A" o="root" g="wheel" p="16877"><f n="Resources" o="root" g="wheel" p="16877"><f n="BridgeSupport" o="root" g="wheel" p="16877"><f n="Kerberos.bridgesupport" o="root" g="wheel" p="33188"/></f></f></f></f></f><f n="LatentSemanticMapping.framework" o="root" g="wheel" p="16877"><f n="Versions" o="root" g="wheel" p="16877"><f n="A" o="root" g="wheel" p="16877"><f n="Resources" o="root" g="wheel" p="16877"><f n="BridgeSupport" o="root" g="wheel" p="16877"><f n="LatentSemanticMapping.bridgesupport" o="root" g="wheel" p="33188"/></f></f></f></f></f><f n="LDAP.framework" o="root" g="wheel" p="16877"><f n="Versions" o="root" g="wheel" p="16877"><f n="A" o="root" g="wheel" p="16877"><f n="Resources" o="root" g="wheel" p="16877"><f n="BridgeSupport" o="root" g="wheel" p="16877"><f n="LDAP.bridgesupport" o="root" g="wheel" p="33188"/></f></f></f></f></f><f n="Message.framework" o="root" g="wheel" p="16877"><f n="Versions" o="root" g="wheel" p="16877"><f n="B" o="root" g="wheel" p="16877"><f n="Resources" o="root" g="wheel" p="16877"><f n="BridgeSupport" o="root" g="wheel" p="16877"><f n="Message.bridgesupport" o="root" g="wheel" p="33188"/></f></f></f></f></f><f n="NetFS.framework" o="root" g="wheel" p="16877"><f n="Versions" o="root" g="wheel" p="16877"><f n="A" o="root" g="wheel" p="16877"><f n="Resources" o="root" g="wheel" p="16877"><f n="BridgeSupport" o="root" g="wheel" p="16877"><f n="NetFS.bridgesupport" o="root" g="wheel" p="33188"/></f></f></f></f></f><f n="OpenAL.framework" o="root" g="wheel" p="16877"><f n="Versions" o="root" g="wheel" p="16877"><f n="A" o="root" g="wheel" p="16877"><f n="Resources" o="root" g="wheel" p="16877"><f n="BridgeSupport" o="root" g="wheel" p="16877"><f n="OpenAL.bridgesupport" o="root" g="wheel" p="33188"/></f></f></f></f></f><f n="OpenCL.framework" o="root" g="wheel" p="16877"><f n="Versions" o="root" g="wheel" p="16877"><f n="A" o="root" g="wheel" p="16877"><f n="Resources" o="root" g="wheel" p="16877"><f n="BridgeSupport" o="root" g="wheel" p="16877"><f n="OpenCL.bridgesupport" o="root" g="wheel" p="33188"/></f></f></f></f></f><f n="OpenDirectory.framework" o="root" g="wheel" p="16877"><f n="Versions" o="root" g="wheel" p="16877"><f n="A" o="root" g="wheel" p="16877"><f n="Frameworks" o="root" g="wheel" p="16877"><f n="CFOpenDirectory.framework" o="root" g="wheel" p="16877"><f n="Versions" o="root" g="wheel" p="16877"><f n="A" o="root" g="wheel" p="16877"><f n="Resources" o="root" g="wheel" p="16877"><f n="BridgeSupport" o="root" g="wheel" p="16877"><f n="CFOpenDirectory.bridgesupport" o="root" g="wheel" p="33188"/></f></f></f></f></f></f><f n="Resources" o="root" g="wheel" p="16877"><f n="BridgeSupport" o="root" g="wheel" p="16877"><f n="OpenDirectory.bridgesupport" o="root" g="wheel" p="33188"/></f></f></f></f></f><f n="OpenGL.framework" o="root" g="wheel" p="16877"><f n="Versions" o="root" g="wheel" p="16877"><f n="A" o="root" g="wheel" p="16877"><f n="Resources" o="root" g="wheel" p="16877"><f n="BridgeSupport" o="root" g="wheel" p="16877"><f n="OpenGL.bridgesupport" o="root" g="wheel" p="33188"/></f></f></f></f></f><f n="OSAKit.framework" o="root" g="wheel" p="16877"><f n="Versions" o="root" g="wheel" p="16877"><f n="A" o="root" g="wheel" p="16877"><f n="Resources" o="root" g="wheel" p="16877"><f n="BridgeSupport" o="root" g="wheel" p="16877"><f n="OSAKit.bridgesupport" o="root" g="wheel" p="33188"/></f></f></f></f></f><f n="PCSC.framework" o="root" g="wheel" p="16877"><f n="Versions" o="root" g="wheel" p="16877"><f n="A" o="root" g="wheel" p="16877"><f n="Resources" o="root" g="wheel" p="16877"><f n="BridgeSupport" o="root" g="wheel" p="16877"><f n="PCSC.bridgesupport" o="root" g="wheel" p="33188"/></f></f></f></f></f><f n="PreferencePanes.framework" o="root" g="wheel" p="16877"><f n="Versions" o="root" g="wheel" p="16877"><f n="A" o="root" g="wheel" p="16877"><f n="Resources" o="root" g="wheel" p="16877"><f n="BridgeSupport" o="root" g="wheel" p="16877"><f n="PreferencePanes.bridgesupport" o="root" g="wheel" p="33188"/></f></f></f></f></f><f n="PubSub.framework" o="root" g="wheel" p="16877"><f n="Versions" o="root" g="wheel" p="16877"><f n="A" o="root" g="wheel" p="16877"><f n="Resources" o="root" g="wheel" p="16877"><f n="BridgeSupport" o="root" g="wheel" p="16877"><f n="PubSub.bridgesupport" o="root" g="wheel" p="33188"/></f></f></f></f></f><f n="Python.framework" o="root" g="wheel" p="16877"><f n="Versions" o="root" g="wheel" p="16877"><f n="2.6" o="root" g="wheel" p="16877"><f n="Resources" o="root" g="wheel" p="16877"><f n="BridgeSupport" o="root" g="wheel" p="16877"><f n="Python.bridgesupport" o="root" g="wheel" p="33188"/></f></f></f></f></f><f n="QTKit.framework" o="root" g="wheel" p="16877"><f n="Versions" o="root" g="wheel" p="16877"><f n="A" o="root" g="wheel" p="16877"><f n="Resources" o="root" g="wheel" p="16877"><f n="BridgeSupport" o="root" g="wheel" p="16877"><f n="QTKit.bridgesupport" o="root" g="wheel" p="33188"/></f></f></f></f></f><f n="Quartz.framework" o="root" g="wheel" p="16877"><f n="Versions" o="root" g="wheel" p="16877"><f n="A" o="root" g="wheel" p="16877"><f n="Frameworks" o="root" g="wheel" p="16877"><f n="ImageKit.framework" o="root" g="wheel" p="16877"><f n="Versions" o="root" g="wheel" p="16877"><f n="A" o="root" g="wheel" p="16877"><f n="Resources" o="root" g="wheel" p="16877"><f n="BridgeSupport" o="root" g="wheel" p="16877"><f n="ImageKit.bridgesupport" o="root" g="wheel" p="33188"/></f></f></f></f></f><f n="PDFKit.framework" o="root" g="wheel" p="16877"><f n="Versions" o="root" g="wheel" p="16877"><f n="A" o="root" g="wheel" p="16877"><f n="Resources" o="root" g="wheel" p="16877"><f n="BridgeSupport" o="root" g="wheel" p="16877"><f n="PDFKit.bridgesupport" o="root" g="wheel" p="33188"/></f></f></f></f></f><f n="QuartzComposer.framework" o="root" g="wheel" p="16877"><f n="Versions" o="root" g="wheel" p="16877"><f n="A" o="root" g="wheel" p="16877"><f n="Resources" o="root" g="wheel" p="16877"><f n="BridgeSupport" o="root" g="wheel" p="16877"><f n="QuartzComposer.bridgesupport" o="root" g="wheel" p="33188"/></f></f></f></f></f><f n="QuartzFilters.framework" o="root" g="wheel" p="16877"><f n="Versions" o="root" g="wheel" p="16877"><f n="A" o="root" g="wheel" p="16877"><f n="Resources" o="root" g="wheel" p="16877"><f n="BridgeSupport" o="root" g="wheel" p="16877"><f n="QuartzFilters.bridgesupport" o="root" g="wheel" p="33188"/></f></f></f></f></f><f n="QuickLookUI.framework" o="root" g="wheel" p="16877"><f n="Versions" o="root" g="wheel" p="16877"><f n="A" o="root" g="wheel" p="16877"><f n="Resources" o="root" g="wheel" p="16877"><f n="BridgeSupport" o="root" g="wheel" p="16877"><f n="QuickLookUI.bridgesupport" o="root" g="wheel" p="33188"/></f></f></f></f></f></f><f n="Resources" o="root" g="wheel" p="16877"><f n="BridgeSupport" o="root" g="wheel" p="16877"><f n="Quartz.bridgesupport" o="root" g="wheel" p="33188"/></f></f></f></f></f><f n="QuartzCore.framework" o="root" g="wheel" p="16877"><f n="Versions" o="root" g="wheel" p="16877"><f n="A" o="root" g="wheel" p="16877"><f n="Resources" o="root" g="wheel" p="16877"><f n="BridgeSupport" o="root" g="wheel" p="16877"><f n="QuartzCore.bridgesupport" o="root" g="wheel" p="33188"/></f></f></f></f></f><f n="QuickLook.framework" o="root" g="wheel" p="16877"><f n="Versions" o="root" g="wheel" p="16877"><f n="A" o="root" g="wheel" p="16877"><f n="Resources" o="root" g="wheel" p="16877"><f n="BridgeSupport" o="root" g="wheel" p="16877"><f n="QuickLook.bridgesupport" o="root" g="wheel" p="33188"/></f></f></f></f></f><f n="Ruby.framework" o="root" g="wheel" p="16877"><f n="Versions" o="root" g="wheel" p="16877"><f n="1.8" o="root" g="wheel" p="16877"><f n="Resources" o="root" g="wheel" p="16877"><f n="BridgeSupport" o="root" g="wheel" p="16877"><f n="Ruby.bridgesupport" o="root" g="wheel" p="33188"/><f n="Ruby.dylib" o="root" g="wheel" p="33261"/></f></f></f></f></f><f n="RubyCocoa.framework" o="root" g="wheel" p="16877"><f n="Versions" o="root" g="wheel" p="16877"><f n="A" o="root" g="wheel" p="16877"><f n="Resources" o="root" g="wheel" p="16877"><f n="BridgeSupport" o="root" g="wheel" p="16877"><f n="RubyCocoa.bridgesupport" o="root" g="wheel" p="33188"/></f></f></f></f></f><f n="ScreenSaver.framework" o="root" g="wheel" p="16877"><f n="Versions" o="root" g="wheel" p="16877"><f n="A" o="root" g="wheel" p="16877"><f n="Resources" o="root" g="wheel" p="16877"><f n="BridgeSupport" o="root" g="wheel" p="16877"><f n="ScreenSaver.bridgesupport" o="root" g="wheel" p="33188"/><f n="ScreenSaver.dylib" o="root" g="wheel" p="33261"/></f></f></f></f></f><f n="Scripting.framework" o="root" g="wheel" p="16877"><f n="Versions" o="root" g="wheel" p="16877"><f n="A" o="root" g="wheel" p="16877"><f n="Resources" o="root" g="wheel" p="16877"><f n="BridgeSupport" o="root" g="wheel" p="16877"><f n="Scripting.bridgesupport" o="root" g="wheel" p="33188"/></f></f></f></f></f><f n="ScriptingBridge.framework" o="root" g="wheel" p="16877"><f n="Versions" o="root" g="wheel" p="16877"><f n="A" o="root" g="wheel" p="16877"><f n="Resources" o="root" g="wheel" p="16877"><f n="BridgeSupport" o="root" g="wheel" p="16877"><f n="ScriptingBridge.bridgesupport" o="root" g="wheel" p="33188"/></f></f></f></f></f><f n="Security.framework" o="root" g="wheel" p="16877"><f n="Versions" o="root" g="wheel" p="16877"><f n="A" o="root" g="wheel" p="16877"><f n="Resources" o="root" g="wheel" p="16877"><f n="BridgeSupport" o="root" g="wheel" p="16877"><f n="Security.bridgesupport" o="root" g="wheel" p="33188"/></f></f></f></f></f><f n="SecurityFoundation.framework" o="root" g="wheel" p="16877"><f n="Versions" o="root" g="wheel" p="16877"><f n="A" o="root" g="wheel" p="16877"><f n="Resources" o="root" g="wheel" p="16877"><f n="BridgeSupport" o="root" g="wheel" p="16877"><f n="SecurityFoundation.bridgesupport" o="root" g="wheel" p="33188"/></f></f></f></f></f><f n="SecurityInterface.framework" o="root" g="wheel" p="16877"><f n="Versions" o="root" g="wheel" p="16877"><f n="A" o="root" g="wheel" p="16877"><f n="Resources" o="root" g="wheel" p="16877"><f n="BridgeSupport" o="root" g="wheel" p="16877"><f n="SecurityInterface.bridgesupport" o="root" g="wheel" p="33188"/></f></f></f></f></f><f n="ServerNotification.framework" o="root" g="wheel" p="16877"><f n="Versions" o="root" g="wheel" p="16877"><f n="A" o="root" g="wheel" p="16877"><f n="Resources" o="root" g="wheel" p="16877"><f n="BridgeSupport" o="root" g="wheel" p="16877"><f n="ServerNotification.bridgesupport" o="root" g="wheel" p="33188"/></f></f></f></f></f><f n="ServiceManagement.framework" o="root" g="wheel" p="16877"><f n="Versions" o="root" g="wheel" p="16877"><f n="A" o="root" g="wheel" p="16877"><f n="Resources" o="root" g="wheel" p="16877"><f n="BridgeSupport" o="root" g="wheel" p="16877"><f n="ServiceManagement.bridgesupport" o="root" g="wheel" p="33188"/></f></f></f></f></f><f n="SyncServices.framework" o="root" g="wheel" p="16877"><f n="Versions" o="root" g="wheel" p="16877"><f n="A" o="root" g="wheel" p="16877"><f n="Resources" o="root" g="wheel" p="16877"><f n="BridgeSupport" o="root" g="wheel" p="16877"><f n="SyncServices.bridgesupport" o="root" g="wheel" p="33188"/></f></f></f></f></f><f n="SystemConfiguration.framework" o="root" g="wheel" p="16877"><f n="Versions" o="root" g="wheel" p="16877"><f n="A" o="root" g="wheel" p="16877"><f n="Resources" o="root" g="wheel" p="16877"><f n="BridgeSupport" o="root" g="wheel" p="16877"><f n="SystemConfiguration.bridgesupport" o="root" g="wheel" p="33188"/></f></f></f></f></f><f n="Tcl.framework" o="root" g="wheel" p="16877"><f n="Versions" o="root" g="wheel" p="16877"><f n="8.5" o="root" g="wheel" p="16877"><f n="Resources" o="root" g="wheel" p="16877"><f n="BridgeSupport" o="root" g="wheel" p="16877"><f n="Tcl.bridgesupport" o="root" g="wheel" p="33188"/></f></f></f></f></f><f n="Tk.framework" o="root" g="wheel" p="16877"><f n="Versions" o="root" g="wheel" p="16877"><f n="8.5" o="root" g="wheel" p="16877"><f n="Resources" o="root" g="wheel" p="16877"><f n="BridgeSupport" o="root" g="wheel" p="16877"><f n="Tk.bridgesupport" o="root" g="wheel" p="33188"/></f></f></f></f></f><f n="TWAIN.framework" o="root" g="wheel" p="16877"><f n="Versions" o="root" g="wheel" p="16877"><f n="A" o="root" g="wheel" p="16877"><f n="Resources" o="root" g="wheel" p="16877"><f n="BridgeSupport" o="root" g="wheel" p="16877"><f n="TWAIN.bridgesupport" o="root" g="wheel" p="33188"/></f></f></f></f></f><f n="VideoDecodeAcceleration.framework" o="root" g="wheel" p="16877"><f n="Versions" o="root" g="wheel" p="16877"><f n="A" o="root" g="wheel" p="16877"><f n="Resources" o="root" g="wheel" p="16877"><f n="BridgeSupport" o="root" g="wheel" p="16877"><f n="VideoDecodeAcceleration.bridgesupport" o="root" g="wheel" p="33188"/></f></f></f></f></f><f n="WebKit.framework" o="root" g="wheel" p="16877"><f n="Versions" o="root" g="wheel" p="16877"><f n="A" o="root" g="wheel" p="16877"><f n="Resources" o="root" g="wheel" p="16877"><f n="BridgeSupport" o="root" g="wheel" p="16877"><f n="WebKit.bridgesupport" o="root" g="wheel" p="33188"/></f></f></f></f></f><f n="XgridFoundation.framework" o="root" g="wheel" p="16877"><f n="Versions" o="root" g="wheel" p="16877"><f n="A" o="root" g="wheel" p="16877"><f n="Resources" o="root" g="wheel" p="16877"><f n="BridgeSupport" o="root" g="wheel" p="16877"><f n="XgridFoundation.bridgesupport" o="root" g="wheel" p="33188"/></f></f></f></f></f></f></f></f><f n="usr" o="root" g="wheel" p="16877"><f n="bin" o="root" g="wheel" p="16877"><f n="gen_bridge_metadata" o="root" g="wheel" p="33133"/></f><f n="share" o="root" g="wheel" p="16877"><f n="man" o="root" g="wheel" p="16877"><f n="man1" o="root" g="wheel" p="16877"><f n="gen_bridge_metadata.1" o="root" g="wheel" p="33060"/></f><f n="man5" o="root" g="wheel" p="16877"><f n="BridgeSupport.5" o="root" g="wheel" p="33060"/></f></f></f></f></f></pkg-contents>